crawk/__init__.py
crawk/crawk.py
crawk-0.1.2.dist-info/METADATA
crawk-0.1.2.dist-info/WHEEL
crawk-0.1.2.dist-info/entry_points.txt
crawk-0.1.2.dist-info/top_level.txt
crawk-0.1.2.dist-info/RECORD
