Metadata-Version: 2.2
Name: crawk
Version: 0.1.2
Summary: Crawl a website recursively and save contents as markdown
Author-email: denispcguy <denispcguy@gmail.com>
License: MIT
Requires-Python: >=3.13
Requires-Dist: alive-progress>=3.2.0
Requires-Dist: crawl4ai>=0.4.248
Requires-Dist: pytest>=8.3.4
Requires-Dist: pytest-asyncio>=0.25.3
